{
    "wallpaper": "/home/marcosrdac/cld/Dropbox/home/res/wal/favorites/crater.jpg",
    "alpha": "100",
    "special": {
        "background": "#08192B",
        "foreground": "#d3bdcc",
        "cursor": "#d3bdcc"
    },
    "colors": {
        "color0": "#08192B",
        "color1": "#BF526B",
        "color2": "#646F8F",
        "color3": "#AC738B",
        "color4": "#CE728F",
        "color5": "#E77697",
        "color6": "#7289B3",
        "color7": "#d3bdcc",
        "color8": "#93848e",
        "color9": "#BF526B",
        "color10": "#646F8F",
        "color11": "#AC738B",
        "color12": "#CE728F",
        "color13": "#E77697",
        "color14": "#7289B3",
        "color15": "#d3bdcc"
    }
}