{
    "wallpaper": "/home/marcosrdac/.config/wpg/wallpapers/astronomy-dark-nature-733475.jpg",
    "alpha": "100",

    "special": {
        "background": "#020811",
        "foreground": "#d7fbff",
        "cursor": "#d7fbff"
    },
    "colors": {
        "color0": "#020811",
        "color1": "#084971",
        "color2": "#35534D",
        "color3": "#0F6697",
        "color4": "#08578B",
        "color5": "#4C798E",
        "color6": "#1A6F9F",
        "color7": "#a2bdca",
        "color8": "#041c40",
        "color9": "#02609a",
        "color10": "#3c7469",
        "color11": "#0887cf",
        "color12": "#0173be",
        "color13": "#54a2c6",
        "color14": "#1593da",
        "color15": "#d7fbff"
    }
}
