{
    "wallpaper": "/home/marcosrdac/pictures/wallpapers/tmp/fav_sensorwallhaven-md6owms.jpg",
    "alpha": "100",

    "special": {
        "background": "#0a0407",
        "foreground": "#dbffff",
        "cursor": "#dbffff"
    },
    "colors": {
        "color0": "#0a0407",
        "color1": "#96603B",
        "color2": "#3B9665",
        "color3": "#5A585F",
        "color4": "#4E698E",
        "color5": "#907E7F",
        "color6": "#245363",
        "color7": "#a5c3c2",
        "color8": "#2f1020",
        "color9": "#d07a3f",
        "color10": "#3fd082",
        "color11": "#6f6687",
        "color12": "#5786c6",
        "color13": "#cc9295",
        "color14": "#257089",
        "color15": "#dbffff"
    }
}
